{
    "Items": [
        {
            "jobStatus": {
                "S": "FAILED"
            },
            "failureReason": {
                "S": "process.sh exited with status 1"
            },
            "id": {
                "S": "wjFVG2BCJV3HBwHmJmA7w"
            },
            "jobFailedAt": {
                "S": "2026-06-03T00:07:41.417225+00:00"
            }
        },
        {
            "inputFilePath": {
                "S": "fovus20260531/uploads/afa501c1-2675-4d48-9258-8c7b8dcb8802-test.MD"
            },
            "id": {
                "S": "72f30f8c-a3ea-4547-b63f-e4d68e0fff9d"
            },
            "inputText": {
                "S": "Liangmi Zhang"
            }
        },
        {
            "inputText": {
                "S": "Liangmi Zhang"
            },
            "maxAttempts": {
                "N": "3"
            },
            "inputFilePath": {
                "S": "fovus20260531/test.input"
            },
            "jobStatus": {
                "S": "COMPLETED"
            },
            "attempts": {
                "N": "1"
            },
            "id": {
                "S": "-W7ap6EroOIq51lP-Gi3T"
            },
            "jobStartedAt": {
                "S": "2026-06-03T00:25:49.393Z"
            }
        },
        {
            "inputFilePath": {
                "S": "fovus20260531/uploads/4dfef936-e673-4bb1-bb8c-e8f980a17264-list.txt"
            },
            "id": {
                "S": "44facace-2fa5-4730-b643-37e53f4e4a23"
            },
            "inputText": {
                "S": "new time"
            }
        },
        {
            "inputText": {
                "S": "Liangmi Zhang"
            },
            "maxAttempts": {
                "N": "3"
            },
            "inputFilePath": {
                "S": "fovus20260531/test.input"
            },
            "jobStatus": {
                "S": "COMPLETED"
            },
            "attempts": {
                "N": "1"
            },
            "id": {
                "S": "jl_YPE-Bq5fIqlm0uVQxt"
            },
            "jobStartedAt": {
                "S": "2026-06-03T01:43:47.127Z"
            }
        },
        {
            "inputText": {
                "S": "Liangmi Zhang"
            },
            "maxAttempts": {
                "N": "3"
            },
            "inputFilePath": {
                "S": "fovus20260531/process.sh.input"
            },
            "jobStatus": {
                "S": "COMPLETED"
            },
            "attempts": {
                "N": "1"
            },
            "id": {
                "S": "OeTKrpFNqhQKo7-JCdal9"
            },
            "jobStartedAt": {
                "S": "2026-06-03T00:07:58.566Z"
            }
        },
        {
            "outputText": {
                "S": "  \nLiangmi Zhang 13"
            },
            "id": {
                "S": "unodostreszlm@gmail.com"
            },
            "outputFilePath": {
                "S": "fovus20260531/Liangmi Zhang.output"
            }
        },
        {
            "inputFilePath": {
                "S": "fovus20260531/uploads/bf03d097-6362-4fc6-9da8-be6926ddcdab-test.MD"
            },
            "id": {
                "S": "6bb53a4e-83bd-4f9a-bf01-a4af393f7b61"
            },
            "inputText": {
                "S": "Liangmi Zhang"
            }
        },
        {
            "inputText": {
                "S": "Liangmi Zhang"
            },
            "maxAttempts": {
                "N": "3"
            },
            "inputFilePath": {
                "S": "fovus20260531/process.sh.input"
            },
            "jobStatus": {
                "S": "COMPLETED"
            },
            "attempts": {
                "N": "1"
            },
            "id": {
                "S": "0szGdGYK5FRlvWz_xXtF9"
            },
            "jobStartedAt": {
                "S": "2026-06-02T23:28:08.670Z"
            }
        },
        {
            "inputFilePath": {
                "S": "fovus20260531/uploads/9f105511-590e-43d7-a992-75677973dacd-test.MD"
            },
            "id": {
                "S": "be51f6c8-865c-4ae0-8be7-673419ff1778"
            },
            "inputText": {
                "S": "Liangmi Zhang"
            }
        },
        {
            "inputText": {
                "S": "Liangmi Zhang"
            },
            "maxAttempts": {
                "N": "3"
            },
            "inputFilePath": {
                "S": "fovus20260531/test.input"
            },
            "jobStatus": {
                "S": "COMPLETED"
            },
            "attempts": {
                "N": "1"
            },
            "id": {
                "S": "b_npmnYEixmwp_HQSARtr"
            },
            "jobStartedAt": {
                "S": "2026-06-02T23:09:08.050Z"
            }
        },
        {
            "inputText": {
                "S": "Liangmi Zhang"
            },
            "maxAttempts": {
                "N": "3"
            },
            "inputFilePath": {
                "S": "fovus20260531/test.input"
            },
            "jobStatus": {
                "S": "COMPLETED"
            },
            "attempts": {
                "N": "1"
            },
            "id": {
                "S": "Qpl8_81yTuROOxYz-I6OG"
            },
            "jobStartedAt": {
                "S": "2026-06-03T00:32:47.132Z"
            }
        },
        {
            "inputText": {
                "S": "Liangmi Zhang"
            },
            "maxAttempts": {
                "N": "3"
            },
            "inputFilePath": {
                "S": "fovus20260531/process.sh.input"
            },
            "jobStatus": {
                "S": "COMPLETED"
            },
            "attempts": {
                "N": "1"
            },
            "id": {
                "S": "8H5BDeNKuEscy9W6JU7Fy"
            },
            "jobStartedAt": {
                "S": "2026-06-02T23:13:58.312Z"
            }
        },
        {
            "inputFilePath": {
                "S": "fovus20260531/uploads/3cbae369-b9a7-477c-8c0c-38e4443dd15e-test.MD"
            },
            "id": {
                "S": "beb9e168-c3ca-4cab-b279-442d6c1676b5"
            },
            "inputText": {
                "S": "Liangmi Zhang"
            }
        },
        {
            "inputText": {
                "S": "Liangmi Zhang"
            },
            "maxAttempts": {
                "N": "3"
            },
            "inputFilePath": {
                "S": "fovus20260531/test.input"
            },
            "jobStatus": {
                "S": "COMPLETED"
            },
            "attempts": {
                "N": "1"
            },
            "id": {
                "S": "1_-esW-dVdM7pW_IBmsBA"
            },
            "jobStartedAt": {
                "S": "2026-06-02T16:42:53.743Z"
            }
        },
        {
            "inputFilePath": {
                "S": "fovus20260531/uploads/7b0c79ca-7089-4189-88e9-80c54a24598b-test.MD"
            },
            "id": {
                "S": "4620298f-c10f-41ac-a145-e9ea5fe6801c"
            },
            "inputText": {
                "S": "Liangmi Zhang"
            }
        },
        {
            "inputFilePath": {
                "S": "fovus20260531/uploads/786ceec1-6ad7-4966-a4e5-38238c1e01a9-test.MD"
            },
            "id": {
                "S": "79f1dbed-cc32-4b78-9517-82025ba5454f"
            },
            "inputText": {
                "S": "Liangmi Zhang"
            }
        },
        {
            "inputText": {
                "S": "liangmi zhang"
            },
            "maxAttempts": {
                "N": "3"
            },
            "inputFilePath": {
                "S": "fovus20260531/test.input"
            },
            "jobStatus": {
                "S": "COMPLETED"
            },
            "attempts": {
                "N": "1"
            },
            "id": {
                "S": "X2E-YzxPghcXZCDEFbaoj"
            },
            "jobStartedAt": {
                "S": "2026-06-02T16:33:40.518Z"
            }
        },
        {
            "inputText": {
                "S": "Liangmi Zhang"
            },
            "maxAttempts": {
                "N": "3"
            },
            "inputFilePath": {
                "S": "fovus20260531/test.input"
            },
            "jobStatus": {
                "S": "COMPLETED"
            },
            "attempts": {
                "N": "1"
            },
            "id": {
                "S": "URcYrNkP6J7otc18wrEcG"
            },
            "jobStartedAt": {
                "S": "2026-06-02T14:50:40.863Z"
            }
        },
        {
            "inputFilePath": {
                "S": "fovus20260531/uploads/57a1a7d7-db2a-4106-92b0-334fff495751-test.MD"
            },
            "id": {
                "S": "aafaec7e-14bb-431a-967b-8752bd6346f4"
            },
            "inputText": {
                "S": "Liangmi Zhang"
            }
        },
        {
            "inputFilePath": {
                "S": "fovus20260531/uploads/35eb7271-ed06-4dc8-8721-8ff67600051d-test.MD"
            },
            "id": {
                "S": "3c0a818e-2300-43a0-8c1a-3b4f807ffffa"
            },
            "inputText": {
                "S": "Liangmi Zhang"
            }
        },
        {
            "inputFilePath": {
                "S": "fovus20260531/uploads/37c61cff-5d0b-4076-93fa-68fbd9376256-test.MD"
            },
            "id": {
                "S": "1ab644df-35de-408d-bf2e-bf8ad41a7ecd"
            },
            "inputText": {
                "S": "Liangmi Zhang"
            }
        },
        {
            "inputText": {
                "S": "Liangmi Zhang"
            },
            "maxAttempts": {
                "N": "3"
            },
            "inputFilePath": {
                "S": "fovus20260531/test.input"
            },
            "jobStatus": {
                "S": "COMPLETED"
            },
            "attempts": {
                "N": "1"
            },
            "id": {
                "S": "Z0to3b9ejapXnWrClfCXm"
            },
            "jobStartedAt": {
                "S": "2026-06-03T02:42:20.480Z"
            }
        },
        {
            "inputFilePath": {
                "S": "fovus20260531/uploads/81cafecd-2ee6-404e-99ac-ac7b3779b3ce-test.MD"
            },
            "id": {
                "S": "0a10399b-3605-493b-a95f-b591298d9d7b"
            },
            "inputText": {
                "S": "Liangmi Zhang"
            }
        },
        {
            "inputText": {
                "S": "Liangmi Zhang"
            },
            "maxAttempts": {
                "N": "3"
            },
            "inputFilePath": {
                "S": "fovus20260531/test.input"
            },
            "jobStatus": {
                "S": "COMPLETED"
            },
            "attempts": {
                "N": "1"
            },
            "id": {
                "S": "yqQKCZf217Jzp2G3DZVpM"
            },
            "jobStartedAt": {
                "S": "2026-06-03T01:39:08.306Z"
            }
        },
        {
            "inputFilePath": {
                "S": "fovus20260531/uploads/01b62d46-717c-4f01-b4d0-04acc872433b-test.MD"
            },
            "id": {
                "S": "4e9a1a3b-3892-495e-9d54-d21e7c8fbf92"
            },
            "inputText": {
                "S": "Liangmi Zhang"
            }
        },
        {
            "inputText": {
                "S": "Liangmi Zhang"
            },
            "maxAttempts": {
                "N": "3"
            },
            "inputFilePath": {
                "S": "fovus20260531/test.input"
            },
            "jobStatus": {
                "S": "COMPLETED"
            },
            "attempts": {
                "N": "1"
            },
            "id": {
                "S": "bTvSVYqZ8QTRofKi0QmpD"
            },
            "jobStartedAt": {
                "S": "2026-06-03T01:03:13.948Z"
            }
        },
        {
            "inputFilePath": {
                "S": "fovus20260531/uploads/febaa794-245d-48f8-9ded-b215bf1684e0-test.MD"
            },
            "id": {
                "S": "4422e6de-f47b-4b9e-a3ad-5b885d3c3555"
            },
            "inputText": {
                "S": "Liangmi Zhang"
            }
        },
        {
            "inputText": {
                "S": "Liangmi Zhang"
            },
            "maxAttempts": {
                "N": "3"
            },
            "inputFilePath": {
                "S": "fovus20260531/test.input"
            },
            "jobStatus": {
                "S": "COMPLETED"
            },
            "attempts": {
                "N": "1"
            },
            "id": {
                "S": "jS1vK7ddo0TIoJpJg3aAG"
            },
            "jobStartedAt": {
                "S": "2026-06-03T00:55:45.038Z"
            }
        },
        {
            "inputFilePath": {
                "S": "fovus20260531/uploads/2e49076a-1179-44b2-9a12-ca49dcff4e85-test.MD"
            },
            "id": {
                "S": "d9745413-3fa3-4431-9cd2-0d29a9c483b6"
            },
            "inputText": {
                "S": "Liangmi Zhang"
            }
        }
    ],
    "Count": 30,
    "ScannedCount": 30,
    "ConsumedCapacity": null
}
